berhoel/helper/__init__.py
berhoel/helper/check_args.py
berhoel/helper/machar.py
berhoel/helper/py.typed
berhoel/helper/set_version.py
berhoel/helper/tests/.ruff.toml
berhoel/helper/tests/test_berhoel_helper.py
berhoel/helper/tests/test_check_args.py
berhoel/helper/tests/test_machar.py
bhoelhelper-1.3.9.dist-info/LICENSE
bhoelhelper-1.3.9.dist-info/METADATA
bhoelhelper-1.3.9.dist-info/WHEEL
bhoelhelper-1.3.9.dist-info/entry_points.txt
bhoelhelper-1.3.9.dist-info/RECORD
