Metadata-Version: 2.3
Name: bhoelHelper
Version: 1.3.9
Summary: Misc helper functionalities.
License: MIT
Author: Berthold Höllmann
Author-email: berthold@xn--hllmanns-n4a.de
Maintainer: Berthold Höllmann
Maintainer-email: berthold@xn--hllmanns-n4a.de
Requires-Python: >=3.11,<4.0
Classifier: Development Status :: 5 - Production/Stable
Classifier: License :: OSI Approved :: MIT License
Classifier: Programming Language :: Python :: 3
Classifier: Programming Language :: Python :: 3.11
Classifier: Programming Language :: Python :: 3.12
Classifier: Programming Language :: Python :: 3.13
Classifier: Topic :: Utilities
Requires-Dist: tomli (>=2.0.1,<3.0.0)
